README.md
setup.py
signal_processing/__init__.py
signal_processing/signal_processing.py
signal_processing.egg-info/PKG-INFO
signal_processing.egg-info/SOURCES.txt
signal_processing.egg-info/dependency_links.txt
signal_processing.egg-info/top_level.txt