Metadata-Version: 2.1
Name: signal-processing
Version: 0.0.5
Summary: This repository provides some helper functions for signal processing functions related to time series (in Python).
Home-page: https://github.com/daroodar/TimeSeriesSignalProcessing
Author: Osama Dar
Author-email: osamadar1996@gmail.com
License: UNKNOWN
Platform: UNKNOWN
Classifier: Programming Language :: Python :: 2
Classifier: License :: OSI Approved :: MIT License
Classifier: Operating System :: OS Independent
